relax_gen/__init__.py
relax_gen-0.4.1.dist-info/licenses/LICENSE
relaxgen/__init__.py
relaxgen/gen.py
relax_gen-0.4.1.dist-info/METADATA
relax_gen-0.4.1.dist-info/WHEEL
relax_gen-0.4.1.dist-info/top_level.txt
relax_gen-0.4.1.dist-info/RECORD
