Metadata-Version: 2.4
Name: relax-gen
Version: 0.4.1
Summary: Optimization algorithms library focused on evolutionary methods
Author-email: Luis <luisirach54@gmail.com>
Project-URL: Repositorio, https://github.com/LuisPablo54/relax_gen
Project-URL: Documentación, https://github.com/LuisPablo54/relax_gen/wiki
Requires-Python: >=3.11
License-File: LICENSE
Requires-Dist: numpy
Requires-Dist: pandas
Dynamic: license-file
